[
    {
        "tenhang":"Midea MRC04M3AWW Single Door Chest Freezer, 3.5 Cubic Feet, White",
        "id":69,
        "giatien":"$260.20",
        "hinhanh":"Img/Refrigeration/Freezers/Freezer 1.jpg",
        "link":"https://www.youtube.com/watch?v=7zWuxg-hzBc"
    },
    {
        "tenhang":"Commercial Chest Freezer - Kitma 9.6 Cu. Ft Deep Ice Cream Freezer with 2 Storage Baskets, Adjustable Thermostat, Lock,Rollers, White",
        "id":70,
        "giatien":"$199.99",
        "hinhanh":"Img/Refrigeration/Freezers/Freezer 2.jpg",
        "link":"https://www.youtube.com/watch?v=KZXTuQWFk5c"
    },
    {
        "tenhang":"Whynter CUF-110B Energy Star 1.1 Cubic Feet Upright Lock, Black Freezer, cu ft",
        "id":71,
        "giatien":"$257.83",
        "hinhanh":"Img/Refrigeration/Freezers/Freezer 3.jpg",
        "link":"https://www.youtube.com/watch?v=Cnz7YUeo-AQ"
    },
    {
        "tenhang":"Midea MRC070S0AWW Chest Freezer, 7.0 Cubic Feet, White",
        "id":72,
        "giatien":"$219.89",
        "hinhanh":"Img/Refrigeration/Freezers/Freezer 4.jpg",
        "link":"https://www.youtube.com/watch?v=qiqvCetzU6I"
    },
    {
        "tenhang":"Frigidaire EFRF696-AMZ Upright Freezer 6.5 cu ft Stainless Platinum Design Series",
        "id":73,
        "giatien":"$788.80",
        "hinhanh":"Img/Refrigeration/Freezers/Freezer 5.jpg",
        "link":"https://www.youtube.com/watch?v=mVHEAKL_8UU"
    },
    {
        "tenhang":"5 cu ft Chest Freezer for Your House, Garage, Basement, Apartment, Kitchen, Cabin, Lake House, Timeshare, or Business",
        "id":74,
        "giatien":"$316.89",
        "hinhanh":"Img/Refrigeration/Freezers/Freezer 6.jpg",
        "link":"https://www.youtube.com/watch?v=62iN5o2sfBo"
    }



]